{
  "$schema": "https://json-schema.org/draft/2020-12/schema",
  "$id": "https://researchartifacts.github.io/data-schemas/schemas/artifacts.schema.json",
  "title": "Artifact Collection",
  "description": "Collection of research artifacts from systems and security conferences, including evaluation badges and repository links. Generated by the artifact_analysis pipeline.",
  "type": "array",
  "items": {
    "$ref": "#/$defs/Artifact"
  },
  "$defs": {
    "Artifact": {
      "type": "object",
      "title": "Artifact",
      "description": "A single research artifact associated with a conference paper.",
      "required": [
        "conference",
        "category",
        "year",
        "title",
        "badges",
        "artifact_urls"
      ],
      "properties": {
        "conference": {
          "type": "string",
          "description": "Conference abbreviation where the paper was published.",
          "enum": [
            "ACSAC",
            "ATC",
            "CHES",
            "EUROSYS",
            "FAST",
            "NDSS",
            "OSDI",
            "PETS",
            "SC",
            "SOSP",
            "SYSTEX",
            "USENIXSEC",
            "WOOT"
          ]
        },
        "category": {
          "type": "string",
          "description": "Research domain category.",
          "enum": ["systems", "security"]
        },
        "year": {
          "type": "integer",
          "description": "Publication year.",
          "minimum": 2017,
          "maximum": 2030
        },
        "title": {
          "type": "string",
          "description": "Paper title."
        },
        "badges": {
          "type": "array",
          "description": "Artifact evaluation badges awarded to this artifact. Canonical values: 'available', 'functional', 'reproduced', 'reusable', 'replicated'. Some conferences use non-normalized variants (e.g., 'Badges: Available', 'Functional', 'Artifacts Available + Functional').",
          "items": {
            "type": "string"
          }
        },
        "repository_url": {
          "type": "string",
          "description": "DEPRECATED: Use artifact_urls instead. Kept for backward compatibility.",
          "format": "uri-reference"
        },
        "artifact_url": {
          "oneOf": [
            {
              "type": "string",
              "format": "uri-reference"
            },
            {
              "type": "array",
              "items": {
                "type": "string",
                "format": "uri"
              }
            }
          ],
          "description": "DEPRECATED: Use artifact_urls instead. Kept for backward compatibility."
        },
        "artifact_urls": {
          "type": "array",
          "description": "All artifact-related URLs (repositories, archives, DOIs). Canonical field replacing repository_url, artifact_url, and github_url.",
          "items": {
            "type": "string",
            "format": "uri"
          }
        },
        "paper_url": {
          "type": "string",
          "description": "DOI or direct link to the published paper.",
          "format": "uri"
        },
        "appendix_url": {
          "type": "string",
          "description": "URL to supplementary materials or appendix.",
          "format": "uri"
        },
        "award": {
          "type": "string",
          "description": "Award designation, if any (e.g., 'Distinguished Artifact')."
        }
      },
      "additionalProperties": false
    }
  }
}
